lilliepy_tags/__init__.py
lilliepy_tags/main.py
lilliepy_tags-1.0.0.dist-info/METADATA
lilliepy_tags-1.0.0.dist-info/WHEEL
lilliepy_tags-1.0.0.dist-info/top_level.txt
lilliepy_tags-1.0.0.dist-info/RECORD
