Metadata-Version: 2.4
Name: lilliepy-tags
Version: 1.0.0
Summary: jsx like tag system for reactpy library or lilliepy framework
Author: Sarthak Ghoshal
Author-email: sarthak22.ghoshal@gmail.com
License: MIT
Keywords: lilliepy,lilliepy-tags,reactpy
Classifier: Programming Language :: Python :: 3
Classifier: License :: OSI Approved :: MIT License
Classifier: Operating System :: OS Independent
Requires-Python: >=3.6
Dynamic: author
Dynamic: author-email
Dynamic: classifier
Dynamic: description
Dynamic: description-content-type
Dynamic: keywords
Dynamic: license
Dynamic: requires-python
Dynamic: summary
